LICENSE
MANIFEST.in
README.md
requirements.txt
setup.py
test_gpsimage.py
gpsimage/__init__.py
gpsimage/api.py
gpsimage/base.py
gpsimage.egg-info/PKG-INFO
gpsimage.egg-info/SOURCES.txt
gpsimage.egg-info/dependency_links.txt
gpsimage.egg-info/not-zip-safe
gpsimage.egg-info/requires.txt
gpsimage.egg-info/top_level.txt