Metadata-Version: 1.1
Name: gpsimage
Version: 0.0.2
Summary: Retrieves GPS data from Geo-referenced images made easy
Home-page: https://github.com/DenisCarriere/gpsimage
Author: Denis Carriere
Author-email: carriere.denis@gmail.com
License: Apache License
